{"type":"footer","name":"Footer","sections":{"1766139899491e040c":{"type":"_blocks","blocks":{"ai_gen_block_d812cfc_PRCwjY":{"type":"ai_gen_block_d812cfc","settings":{"title":"Get In Touch","subtitle":"Have a question or want to work together? We'd love to hear from you.","name_label":"Your Name","email_label":"Email Address","show_phone":true,"phone_label":"Phone Number","message_label":"Your Message","submit_text":"Send Message","success_message":"Thank you! Your message has been sent successfully.","max_width":700,"section_padding_top":80,"section_padding_bottom":80,"form_padding":50,"title_size":48,"subtitle_size":16,"background_color":"#ffffff","title_color":"#1d3686","subtitle_color":"#5c6aa1","accent_glow_color":"#1d3686","form_background":"#1d3686","form_border_color":"#ffffff21","border_radius":24,"blur_strength":16,"shadow_color":"#000000","shadow_opacity":"30","noise_opacity":3,"input_background":"#ffffff08","input_focus_background":"#ffffff12","input_border_color":"#ffffff26","input_text_color":"#ffffff","label_color":"#a0a8c8","input_border_radius":12,"button_background":"#0066ff","button_hover_background":"#0052cc","button_text_color":"#ffffff","button_border_radius":12,"success_background":"#00ff4114","success_text_color":"#00ff41","success_border_color":"#00ff4140","error_background":"#ff004114","error_text_color":"#ff6b6b","error_border_color":"#ff004140"},"blocks":{}}},"block_order":["ai_gen_block_d812cfc_PRCwjY"],"settings":{"content_direction":"column","vertical_on_mobile":true,"horizontal_alignment":"flex-start","vertical_alignment":"center","align_baseline":false,"horizontal_alignment_flex_direction_column":"flex-start","vertical_alignment_flex_direction_column":"center","gap":12,"section_width":"page-width","section_height":"","section_height_custom":50,"color_scheme":"","background_media":"none","video_position":"cover","background_image_position":"cover","border":"none","border_width":1,"border_opacity":100,"border_radius":0,"toggle_overlay":false,"overlay_color":"#00000026","overlay_style":"solid","gradient_direction":"to top","padding-block-start":0,"padding-block-end":0}},"1766216046cd958f7f":{"type":"_blocks","blocks":{"ai_gen_block_37c6d36_KNhgBt":{"type":"ai_gen_block_37c6d36","settings":{"container_width":1400,"padding_top":80,"padding_bottom":80,"column_gap":60,"border_radius":40,"background_color":"#0e1f53","text_color":"#ffffff","heading_color":"#ffffff","link_color":"#ffffff","link_hover_color":"#60a5fa","heading_size":16,"heading_weight":600,"heading_margin":20,"heading_transform":"uppercase","heading_letter_spacing":1,"link_size":14,"link_opacity":85,"link_spacing":12,"shop_title":"Shop","shop_link_1_text":"All Products","shop_link_1_url":"shopify:\/\/collections\/all","shop_link_2_text":"Earbuds","shop_link_2_url":"shopify:\/\/collections\/air-buds","shop_link_3_text":"Headphones","shop_link_3_url":"shopify:\/\/collections\/earphones","shop_link_4_text":"Power Bank","shop_link_4_url":"shopify:\/\/collections","shop_link_5_text":"Charger","shop_link_5_url":"shopify:\/\/collections\/chargers","shop_link_6_text":"Accessories","shop_link_6_url":"shopify:\/\/collections","help_title":"Help","help_link_1_text":"Blogs","help_link_1_url":"shopify:\/\/blogs\/news","help_link_2_text":"Privacy Policy","help_link_2_url":"shopify:\/\/policies\/privacy-policy","help_link_3_text":"Terms & Conditions","help_link_3_url":"shopify:\/\/policies\/privacy-policy","help_link_4_text":"Shipping & Return Policy","help_link_4_url":"shopify:\/\/policies\/privacy-policy","help_link_5_text":"Contact Us","help_link_5_url":"shopify:\/\/pages\/contact","help_link_6_text":"FAQs","help_link_6_url":"shopify:\/\/collections\/all","company_title":"Company","company_link_1_text":"About Us","company_link_1_url":"shopify:\/\/collections","company_link_2_text":"Careers","company_link_2_url":"","company_link_3_text":"Express Delivery","company_link_3_url":"","company_link_4_text":"Official Brand Outlet","company_link_4_url":"shopify:\/\/blogs\/news\/best-mobiles-under-50000-pakistan-2025","company_link_5_text":"News & Updates","company_link_5_url":"shopify:\/\/blogs\/news","company_link_6_text":"Press","company_link_6_url":"shopify:\/\/blogs\/news","logo":"shopify:\/\/shop_images\/Untitled_design-removebg-preview.png","logo_width":200,"logo_margin":10,"divider_width":4,"divider_spacing":60,"divider_color":"#ffffff","divider_opacity":15,"facebook_url":"","instagram_url":"","youtube_url":"","linkedin_url":"","twitter_url":"","social_icon_size":40,"social_gap":12,"social_margin":24,"social_border_radius":8,"social_bg_color":"#ffffff1a","social_icon_color":"#ffffff","social_hover_bg":"#60a5fa","social_hover_color":"#ffffff","phone":"+92 3488651965","email":"info@junaidtelecom.com","contact_size":14,"contact_gap":12,"contact_margin":24,"show_newsletter":false,"newsletter_title":"Subscribe to Newsletter","newsletter_title_size":14,"newsletter_placeholder":"Your email","newsletter_button":"Subscribe","newsletter_success":"Thanks for subscribing!","input_padding":12,"button_padding":24,"input_font_size":14,"button_font_size":14,"input_border_width":1,"input_border_radius":8,"button_border_radius":8,"input_bg_color":"#ffffff1a","input_text_color":"#ffffff","input_border_color":"#ffffff33","input_placeholder_color":"#ffffff","input_focus_border":"#60a5fa","input_focus_bg":"#ffffff26","button_bg_color":"#60a5fa","button_text_color":"#ffffff","button_hover_bg":"#3b82f6","success_color":"#4ade80","error_color":"#f87171"},"blocks":{}}},"block_order":["ai_gen_block_37c6d36_KNhgBt"],"settings":{"content_direction":"column","vertical_on_mobile":true,"horizontal_alignment":"flex-start","vertical_alignment":"center","align_baseline":false,"horizontal_alignment_flex_direction_column":"flex-start","vertical_alignment_flex_direction_column":"center","gap":12,"section_width":"page-width","section_height":"","section_height_custom":50,"color_scheme":"","background_media":"none","video_position":"cover","background_image_position":"cover","border":"none","border_width":1,"border_opacity":100,"border_radius":0,"toggle_overlay":false,"overlay_color":"#00000026","overlay_style":"solid","gradient_direction":"to top","padding-block-start":0,"padding-block-end":0}}},"order":["1766139899491e040c","1766216046cd958f7f"]}